Metadata-Version: 2.1
Name: Perceptron-pypi-SourabhSomdeve
Version: 0.0.2
Summary: An Implementation of one Neuron Perceptron
Home-page: https://github.com/SourabhSomdeve/Perceptron_pypi
Author: SourabhSomdeve
Author-email: sourabhsomdeve09@gmail.com
License: UNKNOWN
Project-URL: Bug Tracker, https://github.com/SourabhSomdeve/Perceptron_pypi/issues
Platform: UNKNOWN
Classifier: Programming Language :: Python :: 3
Classifier: License :: OSI Approved :: MIT License
Classifier: Operating System :: OS Independent
Requires-Python: >=3.7
License-File: LICENSE
Requires-Dist: numpy
Requires-Dist: tqdm
